{
	"choose_reason": "Выберите причину",
	"reason_cancel": "Отмена",
	"rank_description": "Посмотреть вашу или чужую карту рейтинга сервера.",
	"clear_description": "Удалить сообщения канала.",
	"moveme_description": "Переместить вас в голосовой канал.",
	"profile_description": "Посмотреть вашу или чужую настраиваемую персональную карту общедоступного профиля.",
	"top_description": "Показать участников, набравших наибольшее количество баллов или опыта на сервере.",
	"user_description": "Показать информацию о себе или пользователе, например, ID и дату вступления.",
	"avatar_description": "Показать аватар пользователя.",
	"server_description": "Показать информацию о сервере",
	"roles_description": "Показать список ролей на сервере и количество участников.",
	"ban_description": "Заблокировать участника.",
	"unban_description": "Разблокировать участника.",
	"kick_description": "Выгнать участника.",
	"vkick_description": "Выгнать участника из голосового канала.",
	"mute_description": "Запретить печатать участнику в текстовых каналах.",
	"vmute_description": "Выключить микрофон учасника в голосовых каналах.",
	"unvmute_description": "Включить микрофон участнику. ",
	"move_description": "Переместить участника в голосовой канал.",
	"role_description": "Добавить/забрать у участника роль или роли.",
	"warn_description": "Сделать предупреждение участнику.",
	"setcolor_description": "Поменять цвета ролей с помощью шестнадцатеричных кодов.",
	"warnings_description": "Показать предупреждения пользователей на сервере.",
	"setnick_description": "Сменить никнейм участнику.",
	"play_description": "Добавить песню в очередь и включить воспроизведение.",
	"skip_description": "Пропустить песню.",
	"search_description": "Поиск результатов для воспроизведения.",
	"queue_description": "Показать очередь текущих песен в списке воспроизведения.",
	"stop_description": "Остановить текущую песню и очистить всю очередь воспроизведения музыки.",
	"vol_description": "Изменить/показать текущий уровень громкости.",
	"pause_description": "Поставить на паузу воспроизведение.",
	"np_description": "Показать название песни, которую играет бот.",
	"repeat_description": "Переключение между режимами повтора.",
	"seek_description": "Поиск определенной точки в текущей песни.",
	"restore_description": "Восстановить резервную копию!",
	"credits_description": "Показать состояние вашего или чужого счета.",
	"color_description": "Поменять цвет роли.",
	"colors_description": "Перечислить все доступные цвета.",
	"title_description": "Поменять заголовок в вашем `/profile`",
	"reset_description": "Сбросить очки опыта (текстовый/голосовой/приглашения), для всех участников.",
	"rep_description": "Выразить свое уважение к участнику. Можно один раз в сутки.",
	"daily_description": "Получить свою ежедневную зарплату.",
	"vip_description": "Показать информацию о вашем премиум боте.",
	"ping_description": "Проверить время отклика бота.",
	"temp_description": "Временные каналы.",
	"deletebackup_description": "Удалить резервную копию.",
	"short_description": "Сократить URL адрес.",
	"roll_description": "Бросить кости.",
	"points_description": "Баллы, которые могут быть выданы модераторами.",
	"usage": "Применение:",
	"c": "Описание:",
	"aliases": "Псевдонимы:",
	"Language has been changed successfully": ":white_check_mark: язык успешно изменен.",
	"Joined Discord": "Добавлен Discord",
	"Joined Server": "Добавлен Сервер",
	"Invited By": "Пригласил",
	"Last seen in voice channels": "Последние посещение голосового канала.",
	"Online": "В сети",
	"cant_find_member_search_term": ":rolling_eyes: - **{0}**, я не могу найти {1} на сервере.",
	"cant_find_user": ":rolling_eyes: - **{0}**, я не могу найти {1} на сервере.",
	"choose_color": ":rolling_eyes: - Пожалуйста, выберите номер цвета",
	"Color has been removed successfully!": "Цвет был успешно удален!",
	"Requested by": "По запросу",
	"colors_already": ":rolling_eyes: Вы уже выбрали этот цвет.",
	"colors_permission": ":rolling_eyes: **Цвет не может быть использован без разрешения администратора **",
	"colors_done": "Цвет был успешно изменен.",
	"I don't have permission to give you this color": "У меня нет разрешения дать тебе этот цвет.",
	"Wrong color number": "Не правильный номер цвета.",
	"You should enter numbers :1234:": "Вы должны ввести цифры :1234:",
	":rolling_eyes: - **I can't find this command.**": ":rolling_eyes: **Я не могу найти эту команду**",
	"examples": "Примеры:",
	"Invites": "Приглашения",
	"lock_must_has_manage_channels": ":rolling_eyes: ** Для этого нужны права`Управление каналами`",
	"channel_has_been_locked": "**:lock: {0} заблокирован.**",
	"channel_has_been_unlocked": "**:unlock: {0} разблокирован.**",
	"lock_description": "Отключение возможности упоминать @everyone в выбранном канале.",
	"unlock_description": "Удаляет запрещенные для отправки сообщения от @everyone в выбранном канале.",
	"requested_by_embed": "По запросу {0}#{1}",
	"cant_mute_user": ":rolling_eyes: - ** Вы не можете отключить звук пользователю @{0}. **",
	"cant_find_member": ":rolling_eyes: - **Я не могу найти этого пользователя**",
	"mute_user_muted": ":white_check_mark: **@{0} отключен в текстовых каналах :zipper_mouth:**",
	"daily_credits_refreshes_description": "**:rolling_eyes: | {0}, ваш ежедневный доход будет начислен через {1}. **",
	"daily_not_have_rank_description": ":robot: **| {0}**, Боты не участвуют в рейтинге!",
	"daily_credits_got_description": "**:moneybag: {0}, ваш ежедневный доход составил :dollar: {1} !**",
	"daily_user_not_found_description": ":rolling_eyes: **| {0}**, мне не удалось найти пользователя с таким именем.",
	"role_specify_one_description": ":rolling_eyes: - ** Пожалуйста, выберите одну из существующих ролей  **",
	"role_dont_have_access_description": ":rolling_eyes: - У вас нет прав что-бы установить {0}.",
	"role_cant_find_description": ":rolling_eyes: - Я не смог найти указанную роль(и) {0}.",
	"role_cant_find_2_description": ":rolling_eyes: - Я не смог найти указанную роль {0}.",
	"role_couldnt_change_description": ":rolling_eyes: - Я не могу менять роли этому пользователю. Пожалуйста проверь мои права, разрешения и позицию роли.",
	"role_position_higher_description": ":rolling_eyes: - **{0}** расположена(ы) выше, чем ваша.",
	"role_changed_description": ":white_check_mark: Изменена роль для {0}, **{1}**",
	"role_must_have_permission_description": ":rolling_eyes: - ** Для выполнения команды у вас должны быть права Администратора.",
	"role_specify_name_description": ":rolling_eyes: - ** Пожалуйста укажите название роли **",
	"role_changing_for_description": ":white_check_mark: Изменение роли {0} участникам, {1}**{2}**",
	"unvmute_member_voice_description": ":white_check_mark: {0} ограничение снято!",
	"unvmute_not_muted_description": ":blush: **{0} не имеет ограничений.**",
	"ban_from_server_description": ":white_check_mark: **{0} Заблокирован на сервере! :airplane:**",
	"ban_cant_description": ":rolling_eyes: - ** Вы не можете заблокировать @{0}. **",
	"ban_missing_permission_description": ":rolling_eyes: - Я не могу заблокировать пользователя. Пожалуйста проверь мои права, разрешения и позицию роли.",
	"clear_cooldown_description": "**{0}**, Остынь (**{1}** вышел)",
	"clear_cant_description": ":rolling_eyes: - Я не могу очистить этот канал. Пожалуйста проверь мои права доступа.",
	"clear_message_has": "{0} сообщение было удалено.",
	"clear_messages_have": "{0} сообщений было удалено.",
	"kick_cant_description": ":rolling_eyes: - ** Вы не можете выгнать пользователя @{0}. **",
	"kick_couldnt_description": ":rolling_eyes: - Я не могу выгнать пользователя. Пожалуйста проверь мои права доступа.",
	"kick_server_description": ":white_check_mark: **@{0} выгнан с сервера! **",
	"reset_point_done_description": ":white_check_mark: ** Данные статистики успешно сброшены **",
	"yes_description": "да",
	"setcolor_role_name_description": ":rolling_eyes: - ** Пожалуйста укажите название роли **",
	"setcolor_cant_find_description": ":rolling_eyes: ** Не могу найти эту роль ** ",
	"setcolor_miss_permission_description": ":rolling_eyes: ** У вас нет прав доступа к этой роли **",
	"setcolor_cant_change_description": ":rolling_eyes: - Я не могу изменить эту роль. Пожалуйста проверь мои права доступа, разрешения и позицию роли.",
	"setcolor_hex_description": ":rolling_eyes: - Hex должен состоять из 6 или 3 знаков",
	"setcolor_done_description": ":white_check_mark: ** У {0} успешно изменен цвет.**",
	"setcolor_permission_need_description": ":rolling_eyes: ** У меня нет прав доступа к этой роли **",
	"warn_cant_description": ":rolling_eyes: - ** Вы не можете сделать предупреждение пользователю @{0}. **",
	"warn_select_description": "**Выберите причину:**",
	"warn_specify_description": ":rolling_eyes: - **Пожалуйста укажите причину.**",
	"warn_been_removed_description": ":white_check_mark: **{0} предупреждение было удалено.**",
	"warn_cant_warning_description": " **Я не могу найти предупреждение, которое вы ищете.**",
	"warn_specify_number_description": ":rolling_eyes: - **Пожалуйста, напишете номер предупреждения или укажите пользователя или напишите (all) что-бы удалить все предупреждения.**",
	"vkick_cant_permission_description": ":rolling_eyes: - Я не могу выгнать этого пользователя. Пожалуйста проверь мои права доступа и разрешения.",
	"vkick_you_cant_description": ":rolling_eyes: - ** Вы не можете выгнать выгнать пользователя {0}. **",
	"vkick_not_voice_description": ":rolling_eyes: - ** Пользователь не в голосовом канале! **",
	"vkick_voice_kicked_description": ":white_check_mark: **@{0} выгнан из голосового канала **",
	"unban_couldnt_user_description": ":rolling_eyes: - Я не могу разблокировать пользователя. Пожалуйста проверь мои права доступа и разрешения.",
	"unban_all_members_description": ":rolling_eyes: - **Что-бы разблокировать всех пользователей, ты должен обладать правами администратора**",
	"unban_premium_only_description": "Эта команда только для Премиум пользователей (на данный момент).",
	"unban_members_being_description": ":white_check_mark: **{0}** участники были разблокированы",
	"unban_unbanned_description": ":white_check_mark: **{0} разблокирован!**",
	"unban_cant_find_description": ":rolling_eyes: - **Я не могу найти {0} в черном списке**",
	"vmute_main_description": "{0}, Кем: {1}#{2}, ПРИЧИНА: {3} СРОК ДЕЙСТВИЯ: {4}",
	"vmute_muted_from_description": ":white_check_mark: **У @{0} был отключен микрофон! :zipper_mouth:**",
	"vmute_couldnt_mute_description": ":rolling_eyes: - Я не могу отключить этого пользователя. Пожалуйста проверь мои права доступа и разрешения.",
	"vmute_cant_description": ":rolling_eyes: - ** Вы не можете отключить пользователя @{0}. **",
	"setnick_changed_description": ":white_check_mark: **{0}** сменил никнейм на {1}! ",
	"setnick_reset_description": ":white_check_mark: **{0}** восстановил свой никнейм.",
	"setnick_couldnt_update_description": ":rolling_eyes: - Я не могу внести изменения для этого пользователя. Пожалуйста проверь мои права доступа, разрешения и позицию роли.",
	"unmute_cant_find_description": ":rolling_eyes: - **Не могу найти отключенные роли**",
	"unmute_check_permissions_description": ":rolling_eyes: - Пожалуйста проверь мои права доступа, разрешения и позицию роли.",
	"unmute_command_require_description": ":rolling_eyes: - ** Эта команда требует права доступа`Administrator`! **",
	"unmute_unmuting_description": "**Ограничения для  {0} пользователей были сняты.**",
	"link_must_have_description": ":rolling_eyes: - ** Бот должен иметь разрешение `Создавать приглашение` для приглашения на сервер по умолчанию **",
	"link_error_description": ":rolling_eyes: - **Ошибка**",
	"link_cant_find_description": ":rolling_eyes: - **Я не могу найти установленный по умолчанию канал.**",
	"vip_ownership_successfully_description": "** Право владения сервером было успешно передано **",
	"vip_mistake_description": ":rolling_eyes: - Ошибка в орфографии.",
	"vip_twitch_channel_description": "Укажите URL адрес Twitch канала:",
	"vip_wrong_url_description": ":rolling_eyes: - ** Неправильный URL, отменяю... **",
	"vip_changing_description": "**Изменение...** (Это может занять некоторое время из за политики Discord)",
	"vip_done_description": ":white_check_mark: завершено",
	"vip_error_description": "**:rolling_eyes: - Ошибка 503 **",
	"vip_canceling_description": ":rolling_eyes: - ** Отмена ... **",
	"vip_wrong_bot_description": ":rolling_eyes: - Не правильный номер бота.",
	"vip_command_premium_description": "**:rolling_eyes: - Эта команда только премиум-пользователей. Если премиум-бот не может быть найден, можно написать команду с указанием ID или номера бота.**",
	"vip_must_enter_description": "**:rolling_eyes: - Вы должны ввести команду, после которой следует упоминание или id пользователя, которому вы хотите передать бота.",
	"vip_error_id_description": "**:rolling_eyes: - Ошибка в упоминании или ID пользователя**",
	"vip_bans_bots_description": ":rolling_eyes: - **Закон Калифорнии запрещает ботам притворяться людьми** \nhttps://habr.com/ru/company/ashmanov_net/blog/425675/",
	"vip_joke_description": "**Разве я смеюсь над вами?**",
	"vip_confirm_description": "** :innocent: Пожалуйста, напишите `confirm`. **",
	"vip_send_dm_description": "**:rolling_eyes: - Пожалуйста, разрешите боту отправлять прямые сообщения.**",
	"vip_previous_transfer_description": "**:rolling_eyes: - Существует предыдущий запрос на трансфер, новая ссылка была отправлена в ЛС **",
	"vip_transfer_link_description": "**:white_check_mark: Вы можете передать бота использовав ссылку, отправленную вам в ЛС. Срок действия ссылки истекает через 10 минут после ее отправки, после чего вам потребуется запросить ссылку снова.**",
	"vip_link_expired_description": "Срок действия ссылки истек",
	"vip_must_ownership_description": "**:rolling_eyes: - Вы должны быть владельцем этого бота.**",
	"vip_owner_only_description": "Только для владельца~",
	"vip_select_one_description": "** Выберите один вариант: **",
	"vip_restarting_description": ":timer: **Перезагрузка ...**",
	"vip_please_wait_description": "**:stopwatch: | {0}, пожалуйста подождите {1}. **",
	"vip_please_attach_description": ":rolling_eyes: - **Пожалуйста, укажите или прикрепите**",
	"vip_please_specify_description": ":rolling_eyes: - **Пожалуйста уточните**",
	"vip_details_description": "**Премиум Номер:** {0}\n**Премиум закончится** {1}\n**Зарегистрирован для:** {2}",
	"vip_ended_description": "законченный ",
	"slowmode_description": "Enable or disable slowmode on a channel.",
	"slowmode_time_description": "The time to set for slowmode channel.",
	"credits_not_enough": "** :thinking: | {0}, на вашем счете недостаточно средств для этого**",
	"credits_trans_done": "**:moneybag: | {0}, будет переведено`${1}` пользователю {2} **",
	"credits_receipt": ":atm: | Приходный ордер ```Вам поступило на счет ${0} от пользователя {1} (ID: {2})\nReason: {3} \n```",
	"credits_blacklist": ":sweat: ** Ваш аккаунт в черном списке. **",
	"credits_balance": ":bank: | ** {0}, баланс вашего счета составляет `${1}`.**\n",
	"credits_balance_mentions": "** {0} :credit_card: остаток `${1}`.**",
	"credits_cant_find": "** :interrobang: | {0}, Я не могу найти {1}!**",
	"credits_bots": ":thinking: | **{0}**, У бота нет счета!",
	"credits_need_transfer": "** :interrobang: | {0}, Укажите сумму, которую вы хотите перевести!!**",
	"credits_transfer_fees": "** {0}, Комиссия: `{1}`, Итого:`${2}` \n** отправьте указанный код подтверждения :",
	"profile_robot": ":robot: **| {0}**, Боты не участвуют в рейтинге!",
	"profile_cant_find": ":mag: **| {0}**, не удалось найти пользователя.",
	"short_url": "Пожалуйста введите адрес URL",
	"title_long": ":rolling_eyes: - **слишком длинное название.**",
	"avatar_cant_find": ":rolling_eyes: - {0}, Я не могу найти **{1}**!",
	"rep_must_have": ":no_mouth: Ваш уровень должен быть +10. Тогда вы сможете свое выражать уважение другим пользователям.",
	"rep_can_award": "**:stopwatch: | {0}, вы можете снова выразить свое уважение к пользователю через {1}. **",
	"rep_not_bots": ":rolling_eyes: **| {0}**, боты не участвуют в рейтинге!",
	"rep_cannot_give": "**:rolling_eyes: **| {0}**, к сожалению не предусмотрено присвоение очков уважения самому себе!**",
	"rep_given": "**:up: | {0} выразил свое уважения и поднял репутацию на 1 балл пользователю {1} !**",
	"top_only_premium": "В настоящее время в целях повышения производительности данная команда доступна только для премиум-пользователей.",
	"top_error": ":rolling_eyes: - **Ошибка при вводе номера страницы ** {0} from {1} ",
	"top_cant_find_list": "Не могу найти ТОП-лист",
	"top_leaderboards": "📋 Список Лидеров Сервера",
	"top_5text": "**ТОП 5 ТЕКСТ :speech_balloon:**",
	"top_text_score": ":speech_balloon: БАЛЛЫ (ТЕКСТ)",
	"top_5voice": "**TОП 5 ГОЛОС :microphone2:**",
	"top_voice_score": ":microphone2: БАЛЛЫ (ГОЛОС)",
	"top_more": "Далее?",
	"points_title": "Очки:",
	"points_requested": "Разрешил {0}",
	"points_only_managers": ":rolling_eyes: - Управлять баллами могут только менеджеры по баллам.",
	"points_done_reset": ":sparkles: **Все баллы были успешно сброшены.**",
	"points_valid_number": ":rolling_eyes: - **Пожалуйста Используйте Правильный Номер.**",
	"points_target_user": ":sparkles: **{0}** баллов **{1}**",
	"points_new": ":sparkles: **{0}** новые баллы **{1}**.",
	"move_not_in_voice": ":rolling_eyes: - ** Вы не в голосовом канале! **",
	"move_being_moved": ":white_check_mark: ** Все участники были перемещены!**",
	"move_more_specific": ":rolling_eyes: - ** Пожалуйста уточните ** ```{0} ```",
	"move_cant_find": ":rolling_eyes: - **Не могу найти,** {0}",
	"move_already_in": ":white_check_mark: ** {0} уже в голосовом канале!**",
	"move_channel_full": ":rolling_eyes: - ** Этот канал полон! ({0}/{1}) **",
	"move_moved_to": ":white_check_mark: ** {0} перемещен {1}!**",
	"move_ins_perm": ":rolling_eyes: - ** Разрешение не получено **",
	"move_confirm": ":information_source: ** уверены? напишите (y) что-бы подтвердить**",
	"move_cant_find_channel": ":rolling_eyes: - **Я не могу найти указанный канал**",
	"color_error": ":rolling_eyes: - Ошибка с фоном. Если это вдруг случилось, пожалуйста, свяжитесь со службой поддержки",
	"time_reasons_limit": ":rolling_eyes: - **Ограничения времени должны быть равны (h, d, w, m, y)**  ",
	"user_warn_warned": ":white_check_mark: **@{0} предупрежден! **",
	"user_warn_you_are_warned": ":warning: **Вам дали предупреждение!**",
	"server_id": ":id: Сервер ID:",
	"server_created": ":calendar: Создан",
	"server_owned": ":crown: Владелец",
	"server_members": ":busts_in_silhouette:  Участники ({0})",
	"server_members_online": "**{0}** В сети",
	"server_channels": ":speech_balloon: Каналы ({0})",
	"server_channels_value": "**{0}** Текстовых | **{1}** Голосовых",
	"server_others": ":earth_africa: Другие",
	"server_others_value": "**Регион:** {0}\n**Уровень верификации:** {1}",
	"server_roles": ":closed_lock_with_key: Роли ({0})",
	"server_roles_value": "Посмотреть список всех ролей, которые используются  **/roles**",
	"temp_activated": ":white_check_mark: **Функция была успешно активирована**",
	"temp_need_enabled": ":rolling_eyes: - **Временные каналы необходимо включить, для использования этой функции, вы можете сделать это, выполнив следующую команду `/temp on`**",
	"temp_disabled": ":white_check_mark: **Функция была успешно отключена**",
	"temp_updated": ":white_check_mark: **Функция была успешно обновлена**",
	"temp_invalid": "**Недействительные аргументы**",
	"temp_create": "Создать временный канал",
	"music_no_played": "Музыка не играет!",
	"music_now_playing": "**:notes: Сейчас играет {0}....**",
	"music_no_playing": "**:frowning2: Музыка не играет.**",
	"music_current_queue": "**:notes: Текущая очередь | {0} entries**",
	"music_added_ProQueue": ":notes: **{0}** Добавлено в **Очередь** (`{1}`)!",
	"music_must_listening": ":no_entry_sign: Вы, должно быть, слушаете в **{0}**, чтобы использовать это.",
	"music_join_voice": ":no_entry_sign: Вы должны присоединиться к голосовому каналу, чтобы использовать его!",
	"music_under_maintenance": "Музыка находится на обслуживании.",
	"music_searching": ":watch: Поиск ... (`{0}`) ",
	"music_include_query": ":no_entry_sign: Пожалуйста, укажите запрос.",
	"music_under_maintenance2": "В настоящее время осуществляется техническое обслуживание музыкальных каналов, пожалуйста, напишите нам на сервере поддержки.",
	"music_not_found": ":mag: **Не найдено. **",
	"music_new_songs": ":fire: **{0}** Музыка из `{1}` добавлена в **Очередь**!",
	"music_added_to": ":notes: **{0}** Добавлено в **Очередь** (`{1}`)!",
	"music_Resumed": ":notes: Возобновлено **{0}**.",
	"music_must_be": ":no_entry_sign: Необходимо включить музыку, чтобы этим пользоваться!",
	"music_player_paused": ":bulb: Воспроизведение уже находится на паузе! Используйте `/resume` для снятия паузы.",
	"music_paused": ":notes: Пауза **{0}**. Используйте `/resume` to для снятия паузы!",
	"music_player_stopped": ":notes: Воспроизведение остановлено, очередь очищена.",
	"music_example_seek": ":rolling_eyes: - Пример `/seek 2:12`",
	"music_song_not_long": ":rolling_eyes: - Этот трек не настолько продолжительный.",
	"music_volume": ":no_entry_sign: Уровень громкости может составлять от 0 до 150 целых чисел!",
	"music_wrong_skip": ":rolling_eyes: **Неверный номер**",
	"music_skipped": ":notes: Пропущено **{0}** - <@!{1}>",
	"music_volume_changed": "Уровень громкости изменен с`{0}` на `{1}`",
	"music_current_volume": "Текущий уровень громкости `{0}`",
	"music_repeat": ":notes: Режим повтора:",
	"music_Repeat_on": "ВКЛЮЧЕНО",
	"music_Repeat_off": "ВЫКЛЮЧЕНО",
	"Warnings_count": "**{0} Предупреждения** ( {1}/{2})",
	"Warnings_item": "ID предупреждения (**{0}**) - сделал {1}\n{2}\n```{3}```",
	"Warnings_item_user": "Пользователь: {0}",
	"reset_confirm_text": ":thinking: **Вы уверены, что хотите сбросить весь опыт, полученный в текстовых каналах?**",
	"reset_confirm_voice": ":thinking: **Вы уверены, что хотите сбросить весь опыт, полученный в голосовых каналах?**",
	"reset_confirm_invites": ":thinking: **Вы уверены, что хотите сбросить все приглашения?**",
	"logs_responsible_moderator": "**Ответственный модератор:**",
	"logs_reason": "**Причина:**",
	"logs_channel_created": ":house: **Создан канал: `{0}`**",
	"logs_channel_deleted": ":house: ** Удален канал: `{0}`**",
	"logs_channel_updated": ":house: **Обновлен канал: `{0}`**",
	"logs_channel_permissions_updated": ":house: **Обновлены разрешения для канала: `{0}`**",
	"logs_banned_from_server": ":airplane: **{0} Заблокирован на сервере.**",
	"logs_unbanned": ":airplane_arriving: **{0} разблокирован.**",
	"logs_welcome_inviter": "**Пригласил**",
	"logs_welcome_invite_code": "**Код приглашения**",
	"logs_welcome_age": "⏲** Возраст аккаунта:**",
	"logs_joined_server": "**{0} присоединился к серверу.**",
	"logs_member_kicked": ":wave: **{0} выгнан.**",
	"logs_member_left": "**{0} вышел.**",
	"logs_member_updated": "\n:writing_hand: **{0} был обновлен.**",
	"logs_old_nickname": "**Старый Никнейм :**",
	"logs_new_nickname": "**Новый Никнейм :**",
	"logs_member_updated_roles": "**Роли :**",
	"logs_nickname_reset": "{0} сбросил никнейм.",
	"logs_nickname_changed": "{0} поменял никнейм.",
	"logs_role_created": ":family_mmb: **`{0}` Была создана роль.**",
	"logs_role_updated": ":family_mmb: **`{0}` Была обновлена роль.**",
	"logs_role_deleted": ":family_mmb: **`{0}` Была удалена роль.**",
	"logs_role_old_name": "**Старое название**",
	"logs_role_new_name": "**Новое имя**",
	"logs_role_old_mentionable": "**Упоминания ранее**",
	"logs_role_new_mentionable": "**Упоминание теперь**",
	"logs_role_old_hoist": "**Выделение роли ранее**",
	"logs_role_new_hoist": "**Выделение роли теперь**",
	"logs_role_old_color": "**Старый цвет**",
	"logs_role_new_color": "**Новый цвет**",
	"logs_role_new_permissions": "**Новые разрешения**",
	"logs_message_deleted": ":wastebasket: **Сообщение от {0} удалено в {1}.**\n{2}",
	"logs_message_updated": ":pencil2: **Сообщение от {0} изменено в {1}.**",
	"logs_message_updated_content_old": "**До этого**",
	"logs_message_updated_content_new": "**Сейчас**",
	"logs_voice_joined": "**{0} присоединился к голосовому каналу `{1}` .**",
	"logs_voice_left": "**{0} вышел из голосового канала `{1}` .**",
	"logs_voice_switched": "**{0} сменил голосовой канал `{1}` => `{2}`.**",
	"logs_voicestate_updated": "**Голосовое состояние {0} обновлено.**",
	"logs_voicestate_server_mute": "microphone2: ** Микрофон Сервера Отключен **",
	"logs_voicestate_server_deafen": ":speaker: ** Звук Сервера Отключен**",
	"logs_voice_moved": "**{0} перемещено`{1}` => `{2}`.**",
	"logs_voice_disconnected": "**{0} отключился.**",
	"protection_no_backup_to_delete": "**Нет резервной копии для удаления**",
	"protection_backup_deleted": "**Резервная копия удалена**",
	"protection_add_admin_permissions": "**{0} ({1})\nДобавлены административные разрешения для роли:\n{2}\nProBot удалил эти разрешения, никаких действий не требуется**.",
	"protection_permissions_all_following": "Разрешения на все перечисленные ниже функции администратора были удалены:",
	"protection_insert_backup_id": ":rolling_eyes: - **Пожалуйста укажите ID резервной копии**",
	"protection_backup_id_invalid": ":rolling_eyes: - **ID ваше резервной копии недействителен. Пожалуйста, попробуйте еще раз.**",
	"protection_restored": ":white_check_mark: **{0}** : Восстановлено",
	"protection_permissions_removed": ":white_check_mark: **{0}** : Разрешения удалены",
	"protection_removed_from_member": ":white_check_mark: **{0}** : Удалено для пользователя.",
	"protection_action": "**Действие: **",
	"protection_backup_saved": "☁ **Облачное Резервное копирование ролей сохранено.**",
	"protection_restore_backup_use": "чтобы восстановить резервную копию используйте команду: ```#restore {0}```",
	"protection_from_bots": "**{0}** есть боты : {1} \n**Действие было выполнено :slight_smile: **",
	"protection_deleted_auto_role": "**{0} ({1}) удалена авто роль**: {2}.\n**Действие было выполнено...**",
	"protection_limit_exceeded": ":rolling_eyes: - **#{0}** на сегодняшний день лимит превышен.",
	"protection_limit_name": "{0} привесил **{1}** лимит.\n**Действие было выполнено...**",
	"temp_already_enabled": ":x: **Эта функция уже включена, чтобы отключить ее используйте команду`{0} off`.**",
	"reset_confirm_member": "**Вы уверены, что хотите сбросить очки: {0}?**",
	"role_error_managed": ":rolling_eyes: - **{0}** — управляется интеграцией и не может быть назначена. ",
	"jump_to_message": "Перейти к сообщению",
	"credits_no_reason": "Причина не указана.",
	"removewarn_description": "Removes warnings from all members or specific user.",
	"help_description": "Чувствуете себя потерянными?",
	"help_command_description": "Подробная информация о том, как пользоваться командой.",
	"roll_dice": "Кубики",
	"invite_description": "Ищете ссылку для приглашения бота?",
	"new_title_description": "Новое название для установки.",
	"avatar_user_description": "Пользователь, аватар которого необходимо показать.",
	"credits_user_description": "Пользователь для показа/передачи кредитов от/к.",
	"credits_amount_description": "Сумма перевода.",
	"credits_comment_description": "Дополнительный комментарий к операции с кредитами.",
	"profile_user_description": "Пользователь для просмотра профиля.",
	"rank_user_description": "Пользователь для получения звания.",
	"user_user_description": "Пользователь для получения информации о.",
	"top_type_description": "Тип таблицы лидеров - текстовый или голосовой.",
	"top_duration_description": "Период, указанный в таблице лидеров.",
	"top_page_description": "Номер страницы таблицы лидеров.",
	"moveme_input_description": "Канал или пользователь для переноса.",
	"color_number_description": "Количество цветов, заданных в команде /colors",
	"points_increase_description": "Увеличение дополнительного количества очков.",
	"points_user_description": "Пользователь для присвоения очков.",
	"points_points_one": "Очки для повышения.",
	"points_points_two": "Очки для понижения.",
	"points_points_three": "Очки для начисления.",
	"points_decrease_description": "Уменьшить количество очков у пользователя.",
	"points_set_description": "Установите определенное количество очков.",
	"points_reset_description": "Сброс очков со всего сервера или с определенного пользователя.",
	"points_reset_user_description": "Пользователь для сброса очков.",
	"points_list_description": "Показать очки всех пользователей.",
	"points_list_filter_description": "Роль по которой будут начисляться очки.",
	"move_user_description": "Пользователь для перемещения.",
	"move_channel_description": "Канал, в который нужно переместить пользователя.",
	"warnings_user_description": "Пользователь, которому нужно выдавать предупреждения.",
	"warn_remove_input_description": "[Warn id] или [user] или [all] для удаления всех предупреждений.",
	"warn_user_description": "Пользователь, которому нужно выдать предупреждение.",
	"warn_reason_description": "Причина предупреждения.",
	"setnick_user_description": "Пользователь, которому нужно установить ник.",
	"setnick_new_description": "Новый ник.",
	"ban_user_description": "Пользователь для блокировки.",
	"ban_time_description": "Продолжительность блокировки.",
	"ban_reason_description": "Причина блокировки.",
	"unban_user_description": "Пользователь для снятия блокировки.",
	"mute_type_description": "Тип мьюта",
	"mute_user_description": "Пользователь для мьюта.",
	"mute_time_description": "Продолжительность мьюта.",
	"mute_reason_description": "Причина мьюта.",
	"unmute_type_description": "Вид снятия мьюта",
	"unmute_user_description": "Пользователь для снятия мьюта",
	"kick_user_description": "Пользователь для исключения с сервера.",
	"kick_reason_description": "Причина исключения с сервера.",
	"vkick_user_description": "Пользователь, которого нужно выгнать из голосового канала.",
	"lock_channel_description": "Блокировка канала.",
	"unlock_channel_description": "Разблокировка канала",
	"clear_NOM_description": "Количество сообщений для удаления.",
	"clear_FBU_description": "Фильтр по сообщениям пользователей.",
	"clear_FBR_description": "Фильтр по ролям сообщений.",
	"temp_on_description": "включить временные каналы.",
	"temp_off_description": "включить временные каналы.",
	"temp_time_description": "Время через, которое временный канал будет удален.",
	"temp_seconds_description": "Время голосового канала.",
	"temp_max_description": "Пользователь может создавать временные каналы в одно и то же время.",
	"temp_max_number_description": "Максимальное количество каналов, которые могут создавать пользователи, 0 - неограниченно.",
	"role_gives_description": "Дает роль пользователю.",
	"role_removes_description": "Удаляет роль у пользователя.",
	"role_multiple_description": "Дать / удалить роль нескольким пользователям.",
	"role_multiple_role_description": "Роль дать / снять.",
	"role_give_role_description": "Дать роль.",
	"role_remove_role_description": "Удалить роль.",
	"role_give_user_description": "Пользователь, которому нужно дать роль.",
	"role_remove_user_description": "Пользователь, которому нужно удалить роль.",
	"role_pick_type_description": "Выберите тип",
	"setcolor_role_description": "Роль, для которой нужно установить цвет.",
	"timeout_user_description": "Таймаут пользователя",
	"timeout_time_description": "продолжительность таймаута",
	"timeout_reason_description": "Причина заглушения.",
	"untimeout_user_description": "The user to untimeout",
	"give_value": "Выдать",
	"remove_value": "Удалить",
	"all_value": "Все",
	"bots_value": "Боты",
	"humans_value": "Люди",
	"humans_role": "All With Role",
	"text_value": "Текст",
	"voice_value": "Голос",
	"invite_value": "Пригласить",
	"both_value": "Оба",
	"day_value": "День",
	"week_value": "Неделя",
	"month_value": "Месяц",
	"play_song_description": "Песня для поиска или ссылка на песню / soundcloud/ spotify.",
	"search_song_description": "Песня, которую нужно искать.",
	"queue_page_description": "Страница, которую вы ищете.",
	"skip_NOT_description": "Сколько треков пропустить.",
	"seek_position_description": "Выбрать определенную точку",
	"vol_amount_description": "Введите значение для настройки.",
	"resume_description": "Возобновляет текущую приостановленную дорожку.",
	"setlang_description": "Устанавливает предпочтительный язык для бота.",
	"setlang_language_description": "Язык, на который следует перейти.",
	"unmute_description": "Разрешить участнику писать. ",
	"muted_both": ":white_check_mark: **@{0} заглушен в текстовых и голосовых каналах! :zipper_mouth:**",
	"slowmode_set": "This channel slowmode has been set to {0}.",
	"slowmode_should": "Time should be less than or equal to {0}.",
	"slowmode_is": "This channel slowmode is {0}.",
	"slowmode_disabled": "This channel's Slowmode has been disabled.",
	"timeout_done": ":white_check_mark: **@{0} has been timed out!**",
	"timeout_cant": ":rolling_eyes: - ** You can't timeout @{0}. **",
	"timeout_missing_permission": ":rolling_eyes: - I couldn't timeout that user. Please double-check my permissions and role position.",
	"timeout_max_time": ":x: Timeout duration must be lower or equal to 28 days.",
	"untimeout_done": ":white_check_mark: **@{0} has been untimed out.**",
	"untimeout_cant": ":rolling_eyes: - ** You can't untimeout @{0}. **",
	"untimeout_missing_permission": ":rolling_eyes: - I couldn't untimeout that user. Please double-check my permissions and role position.",
	"untimeout_not_timedout": ":x: The member is not timed out.",
	"cant_bots": ":robot: This action cannot be taken against bots.",
	"timeout_description": "Timeout a user from sending messages, react or join voice channels.",
	"untimeout_description": "Remove timeout from a user",
	"logs_timedout": "**{0} has been timed out for {1}**.",
	"logs_timedout_remove": "**{0}'s timeout has been ended / removed.**",
	"leveling_title": "You have received a level reward! 🥳",
	"shuffle_description": "Shuffle the current queue!",
	"shuffle_done": ":twisted_rightwards_arrows: **Shuffled the queue.**",
	"search_placeholder": "Choose a song.",
	"select_someone_else": ":x: This select belong to someone else.",
	"lock_channel_reason_description": "Reason of the lock",
	"confirm": "Confirm",
	"lock_already_locked": "**:x: Channel is already locked {0}.**",
	"reset_type_description": "Select the type of reset",
	"reset_user_description": "The user to reset stats for.",
	"vip_choose_placeholder": "Select a status type.",
	"vip_username_description": "Change the name of your premium bot.",
	"vip_username_name_description": "The name of your premium bot.",
	"vip_status_description": "Change your premium bot's status.",
	"vip_status_status_description": "The status of your premium bot.",
	"vip_move_description": "Move your premium bot to a new server.",
	"vip_move_number_description": "Your premium bot number or ID.",
	"vip_restart_description": "Restart your premium bot.",
	"vip_avatar_description": "Change your premium bot's avatar.",
	"vip_avatar_url_description": "The image URL for your premium bot.",
	"vip_transfer_description": "Transfer ownership of your premium bot to another user.",
	"vip_transfer_user_description": "The user to whom you want to transfer your premium bot.",
	"vip_whitelist_description": "Whitelist a user to allow access to the ProBot panel.",
	"vip_whitelist_user_description": "The user you want to allow or remove access from the ProBot panel.",
	"vip_no_perms": ":x: You need administrator permission to use vip commands.",
	"button_someone_else": ":x: Эта кнопка принадлежит кому-то другому.",
	"setxp_add_description": "Add xp to user.",
	"setxp_add_user_description": "The user you want to add xp to.",
	"setxp_add_xp_description": "The amount of xp to add to the user.",
	"setxp_remove_description": "Remove xp from a user",
	"setxp_remove_user_description": "The user you want to remove xp from",
	"setxp_remove_xp_description": "The amount of xp you want to remove from the user.",
	"setxp_select_type": "**Please select the type of xp.**",
	"setxp_text_select": "Adds xp to the text level",
	"setxp_voice_select": "Adds xp to the voice level",
	"setxp_description": "Sets the user's xp",
	"setxp_type_description": "Type of xp to set either text or voice",
	"setxp_user_description": "The user for whom you want to set xp",
	"setxp_xp_description": "The amount of xp to set to the user",
	"setxp_changed_xp": "**✅ @{0}**'s XP has been updated",
	"setlevel_confirm_message": ":thinking: **Are you sure that you want to set a level for @{0}**?",
	"setxp_premium": ":x: This command is only available for premium subscribers.",
	"setlevel_description": "Sets the user's level",
	"setlevel_user_description": "The user for whom you want to set level",
	"setlevel_type_description": "Type of level to set either text or voice",
	"setlevel_level_description": "The level that you want to set to a user",
	"setlevel_max_level": ":x: The maximum level that can be set is {0}",
	"setxp_confirm_message": ":thinking: **Are you sure that you want to set xp for @{0}**",
	"setlevel_changed_level": "**✅ @{0}**'s Level has been updated",
	"warnings_page_description": "Choose a page number",
	"rr_module_disabled": ":x: Reaction roles module is disabled.",
	"rr_button_cant_role": ":rolling_eyes: - I couldn't update your roles, If you're server admin please double-check my permissions.",
	"rr_no_role_select": ":x: There are no roles linked to this select menu.",
	"rr_role_added": ":white_check_mark: Added **{0}**",
	"rr_role_remove": ":x: Removed **{0}**",
	"rr_role_no_change": ":x: There have been no changes in roles.",
	"rr_no_role_button": ":x: There are no roles linked to this button.",
	"rr_admin_role": ":x: Error with changing roles, Please ensure that the selected role has no administrative permissions, as well as relocate my role above the selected roles.",
	"rr_already_give": ":x: Error with changing **{0}** role, you already have that role.",
	"rr_already_take": ":x: Error with changing **{0}** role, you already don't have that role to remove.",
	"point_list_page_description": "Choose a points page number"
}
